{"networks_and_trajectories_binary_data_3":{"cf_matrix":[{"Edge":22,"Non-Edge":0,"_row":"Edge"},{"Edge":1,"Non-Edge":37,"_row":"Non-Edge"}],"execution.time":[0.4814]},"networks_and_trajectories_binary_data_4":{"cf_matrix":[{"Edge":43,"Non-Edge":0,"_row":"Edge"},{"Edge":1,"Non-Edge":76,"_row":"Non-Edge"}],"execution.time":[1.2168]},"networks_and_trajectories_binary_data_5":{"cf_matrix":[{"Edge":60,"Non-Edge":0,"_row":"Edge"},{"Edge":0,"Non-Edge":140,"_row":"Non-Edge"}],"execution.time":[2.0963]},"networks_and_trajectories_binary_data_6":{"cf_matrix":[{"Edge":97,"Non-Edge":0,"_row":"Edge"},{"Edge":0,"Non-Edge":203,"_row":"Non-Edge"}],"execution.time":[4.3828]},"networks_and_trajectories_binary_data_10":{"cf_matrix":[{"Edge":87,"Non-Edge":0,"_row":"Edge"},{"Edge":0,"Non-Edge":183,"_row":"Non-Edge"}],"execution.time":[27.795]},"networks_and_trajectories_binary_data_15":{"cf_matrix":[{"Edge":172,"Non-Edge":0,"_row":"Edge"},{"Edge":21,"Non-Edge":437,"_row":"Non-Edge"}],"execution.time":[118.054]},"networks_and_trajectories_binary_data_20":{"cf_matrix":[{"Edge":252,"Non-Edge":0,"_row":"Edge"},{"Edge":82,"Non-Edge":806,"_row":"Non-Edge"}],"execution.time":[318.6887]}}
